{"ad_search_list":null,"banner_dark":{"uri":"32e5200049fac86168117","url_list":["https://p9-sign.douyinpic.com/obj/32e5200049fac86168117?lk3s=03ea9982\u0026x-expires=1762578000\u0026x-signature=uT2%2B5J0nhrjVAWjzzTGS93cwLdM%3D\u0026from=65706370","https://p3-sign.douyinpic.com/obj/32e5200049fac86168117?lk3s=03ea9982\u0026x-expires=1762578000\u0026x-signature=OII2ETRVBCVtTvF7PDWudzbvcxY%3D\u0026from=65706370","https://p26-sign.douyinpic.com/obj/32e5200049fac86168117?lk3s=03ea9982\u0026x-expires=1762578000\u0026x-signature=2sxaOVECFHLdtGT%2BROII5VLp9%2B0%3D\u0026from=65706370"]},"banner_light":{"uri":"321f4000f703369c24604","url_list":["https://p11-sign.douyinpic.com/obj/321f4000f703369c24604?lk3s=03ea9982\u0026x-expires=1762578000\u0026x-signature=fhrWJR5z8qcUD%2BpknHPcewnUgf0%3D\u0026from=65706370","https://p3-sign.douyinpic.com/obj/321f4000f703369c24604?lk3s=03ea9982\u0026x-expires=1762578000\u0026x-signature=ew%2Fe7drlZRH5WDehnqgOi1cUMu8%3D\u0026from=65706370","https://p26-sign.douyinpic.com/obj/321f4000f703369c24604?lk3s=03ea9982\u0026x-expires=1762578000\u0026x-signature=srVbjLjy3d7Y1%2FcnS8%2BrLJw8T30%3D\u0026from=65706370"]},"board_tabs":null,"data":{"active_time":"2025-11-08 07:16:46","recommend_list":null,"share_info":{"share_link_desc":"我在看抖音热榜，发现最火的内容，赶快来看！戳这里\u003e\u003e","share_title":"我在看抖音热榜，发现最火的内容，赶快来看！","share_url":"https://www.iesdouyin.com/share/billboard/?id=0"},"trending_desc":"实时上升热点","trending_list":[{"article_detail_count":0,"aweme_infos":null,"discuss_video_count":1,"display_style":0,"drift_info":null,"event_time":1762485235,"group_id":"7562757781892388147","hot_value":0,"hotlist_param":"{\"version\":1}","label":0,"related_words":null,"sentence_id":"2297584","sentence_tag":5000,"video_count":5,"word":"朱婷十五运首秀","word_cover":{"uri":"tos-cn-p-0015/oEsBBQLGLIGoDzJAJfLAeSIeSNI47O3BGBSrWC","url_list":["https://p3-sign.douyinpic.com/tos-cn-p-0015/oEsBBQLGLIGoDzJAJfLAeSIeSNI47O3BGBSrWC~noop.jpeg?lk3s=bfd515bb\u0026x-expires=1762578000\u0026x-signature=o%2BJWm3yRhDh9Sj05RVA5o2h4pNk%3D\u0026from=3218412987","https://p26-sign.douyinpic.com/tos-cn-p-0015/oEsBBQLGLIGoDzJAJfLAeSIeSNI47O3BGBSrWC~noop.jpeg?lk3s=bfd515bb\u0026x-expires=1762578000\u0026x-signature=Tka7UEn2P32wN4dhtjsibACSzQ4%3D\u0026from=3218412987","https://p9-sign.douyinpic.com/tos-cn-p-0015/oEsBBQLGLIGoDzJAJfLAeSIeSNI47O3BGBSrWC~noop.jpeg?lk3s=bfd515bb\u0026x-expires=1762578000\u0026x-signature=QhyYrEztCyHPJeyFLouv5wAfruY%3D\u0026from=3218412987"]},"word_sub_board":null,"word_type":3},{"article_detail_count":0,"aweme_infos":null,"discuss_video_count":1,"display_style":0,"drift_info":null,"event_time":1762500049,"group_id":"7568843497547257097","hot_value":0,"hotlist_param":"{\"version\":1}","label":0,"related_words":null,"sentence_id":"2298000","sentence_tag":7000,"video_count":1,"word":"安世中国：已与荷兰总部“脱钩”","word_cover":{"uri":"tos-cn-p-0015/oAi6VtI0hAzvAhmEi6dsMenBNMNfIgonAqsgIB","url_list":["https://p3-sign.douyinpic.com/tos-cn-p-0015/oAi6VtI0hAzvAhmEi6dsMenBNMNfIgonAqsgIB~noop.jpeg?lk3s=bfd515bb\u0026x-expires=1762578000\u0026x-signature=fsmvCXCXX1KcFOFi857mlO%2BZf%2FA%3D\u0026from=3218412987","https://p9-sign.douyinpic.com/tos-cn-p-0015/oAi6VtI0hAzvAhmEi6dsMenBNMNfIgonAqsgIB~noop.jpeg?lk3s=bfd515bb\u0026x-expires=1762578000\u0026x-signature=7Uqipjg08dwpe9swimc3THbtanc%3D\u0026from=3218412987","https://p26-sign.douyinpic.com/tos-cn-p-0015/oAi6VtI0hAzvAhmEi6dsMenBNMNfIgonAqsgIB~noop.jpeg?lk3s=bfd515bb\u0026x-expires=1762578000\u0026x-signature=vv%2B6lCgcBIHLWQ7YvBwsQNgv17s%3D\u0026from=3218412987"]},"word_sub_board":null,"word_type":3},{"article_detail_count":0,"aweme_infos":null,"discuss_video_count":1,"display_style":0,"drift_info":null,"event_time":1762497074,"group_id":"7569548178112222490","hot_value":0,"hotlist_param":"{\"version\":1}","label":0,"related_words":null,"sentence_id":"2297883","sentence_tag":1003,"video_count":3,"word":"冬天就要当贪睡小呆","word_cover":{"uri":"tos-cn-p-0015c000-ce/oUluiXDgi5y1xhLCMPAB0qamsAIjvzMCjI6OQ","url_list":["https://p26-sign.douyinpic.com/tos-cn-p-0015c000-ce/oUluiXDgi5y1xhLCMPAB0qamsAIjvzMCjI6OQ~noop.jpeg?lk3s=bfd515bb\u0026x-expires=1762578000\u0026x-signature=%2BQONpoGfXez4oHXi%2BYw3DknNuxE%3D\u0026from=3218412987","https://p11-sign.douyinpic.com/tos-cn-p-0015c000-ce/oUluiXDgi5y1xhLCMPAB0qamsAIjvzMCjI6OQ~noop.jpeg?lk3s=bfd515bb\u0026x-expires=1762578000\u0026x-signature=CgNKGz3MQzGwM8b0tdkOF20AdeA%3D\u0026from=3218412987","https://p9-sign.douyinpic.com/tos-cn-p-0015c000-ce/oUluiXDgi5y1xhLCMPAB0qamsAIjvzMCjI6OQ~noop.jpeg?lk3s=bfd515bb\u0026x-expires=1762578000\u0026x-signature=v9MdVRTHKivzrQHXbQysQUWcr7Q%3D\u0026from=3218412987"]},"word_sub_board":[3],"word_type":3},{"article_detail_count":0,"aweme_infos":null,"discuss_video_count":1,"display_style":0,"drift_info":null,"event_time":1762491138,"group_id":"7245914932624708868","hot_value":0,"hotlist_param":"{\"version\":1}","label":0,"related_words":null,"sentence_id":"2297801","sentence_tag":2001,"video_count":1,"word":"一口气看完电影消失的她","word_cover":{"uri":"tos-cn-p-0015/oER7fKYgp4At812VBkFEg0DHACA9cboQQTfYNu","url_list":["https://p3-sign.douyinpic.com/tos-cn-p-0015/oER7fKYgp4At812VBkFEg0DHACA9cboQQTfYNu~noop.jpeg?lk3s=bfd515bb\u0026x-expires=1762578000\u0026x-signature=SYdO0yeTGofkuVW28%2FZ7o9FbtAA%3D\u0026from=3218412987","https://p26-sign.douyinpic.com/tos-cn-p-0015/oER7fKYgp4At812VBkFEg0DHACA9cboQQTfYNu~noop.jpeg?lk3s=bfd515bb\u0026x-expires=1762578000\u0026x-signature=WZX7xERxSFQSqzQWZnyRxOWA7co%3D\u0026from=3218412987","https://p11-sign.douyinpic.com/tos-cn-p-0015/oER7fKYgp4At812VBkFEg0DHACA9cboQQTfYNu~noop.jpeg?lk3s=bfd515bb\u0026x-expires=1762578000\u0026x-signature=MWuqhecGw1BqauimJ3cODwxGv0E%3D\u0026from=3218412987"]},"word_sub_board":null,"word_type":3},{"aweme_infos":null,"discuss_video_count":1,"display_style":0,"drift_info":null,"event_time":1762498238,"group_id":"7567710466694665523","hot_value":0,"hotlist_param":"{\"version\":1}","label":5,"related_words":null,"sentence_id":"2297922","sentence_tag":2002,"video_count":3,"word":"棕眼之谜首播观后感","word_cover":{"uri":"tos-cn-p-0015/ok4BONSgZXEGYChEADaeReIsLBA7wQG3nQ8mfg","url_list":["https://p3-sign.douyinpic.com/tos-cn-p-0015/ok4BONSgZXEGYChEADaeReIsLBA7wQG3nQ8mfg~noop.jpeg?lk3s=bfd515bb\u0026x-expires=1762578000\u0026x-signature=ExsZIPh9k%2FyZv06yDnE8t1lW9Sk%3D\u0026from=3218412987","https://p9-sign.douyinpic.com/tos-cn-p-0015/ok4BONSgZXEGYChEADaeReIsLBA7wQG3nQ8mfg~noop.jpeg?lk3s=bfd515bb\u0026x-expires=1762578000\u0026x-signature=SgCINthLKTSU4D7wdpK0WMxLwG4%3D\u0026from=3218412987","https://p26-sign.douyinpic.com/tos-cn-p-0015/ok4BONSgZXEGYChEADaeReIsLBA7wQG3nQ8mfg~noop.jpeg?lk3s=bfd515bb\u0026x-expires=1762578000\u0026x-signature=FwUrUIt85fd3YplgUoBrGVifIPE%3D\u0026from=3218412987"]},"word_sub_board":null,"word_type":3}],"word_list":[{"article_detail_count":0,"aweme_infos":null,"can_extend_detail":false,"discuss_video_count":1,"display_style":0,"drift_info":null,"event_time":1762491672,"group_id":"6935624107728065824","hot_value":12109842,"hotlist_param":"{\"version\":1}","label":3,"position":1,"related_words":null,"room_count":0,"sentence_id":"2297731","sentence_tag":21000,"video_count":13,"view_count":66214309,"word":"福建舰入列","word_cover":{"uri":"tos-cn-p-0015/o8a1AGGD6QSkLYMPrGeC7fdXf6SL8vBPAIBYKQ","url_list":["https://p3-sign.douyinpic.com/tos-cn-p-0015/o8a1AGGD6QSkLYMPrGeC7fdXf6SL8vBPAIBYKQ~noop.jpeg?lk3s=bfd515bb\u0026x-expires=1762578000\u0026x-signature=FwEed9J%2Ft%2BvrAxbBy4cT%2B4q%2Btcs%3D\u0026from=3218412987","https://p26-sign.douyinpic.com/tos-cn-p-0015/o8a1AGGD6QSkLYMPrGeC7fdXf6SL8vBPAIBYKQ~noop.jpeg?lk3s=bfd515bb\u0026x-expires=1762578000\u0026x-signature=zMUZ9gO8iMNgd02wrFTrP%2BY7eC8%3D\u0026from=3218412987","https://p9-sign.douyinpic.com/tos-cn-p-0015/o8a1AGGD6QSkLYMPrGeC7fdXf6SL8vBPAIBYKQ~noop.jpeg?lk3s=bfd515bb\u0026x-expires=1762578000\u0026x-signature=wBEO4DRii9l3Ieh2lpp7083wfm4%3D\u0026from=3218412987"]},"word_sub_board":null,"word_type":1},{"article_detail_count":0,"aweme_infos":null,"can_extend_detail":false,"discuss_video_count":1,"display_style":0,"drift_info":null,"event_time":1762473483,"group_id":"6814904089575429388","hot_value":11265673,"hotlist_param":"{\"version\":1}","label":3,"position":2,"related_words":null,"sentence_id":"2297374","sentence_tag":3002,"video_count":3,"view_count":57662969,"word":"特朗普痛骂佩洛西","word_cover":{"uri":"tos-cn-p-0015/o87ZAyNieC2fkr0LNgCprIVhIA90IwBV1BYAiB","url_list":["https://p3-sign.douyinpic.com/tos-cn-p-0015/o87ZAyNieC2fkr0LNgCprIVhIA90IwBV1BYAiB~noop.jpeg?lk3s=bfd515bb\u0026x-expires=1762578000\u0026x-signature=biDmyVpcARxgoRHl7DlRA7iAFFM%3D\u0026from=3218412987","https://p26-sign.douyinpic.com/tos-cn-p-0015/o87ZAyNieC2fkr0LNgCprIVhIA90IwBV1BYAiB~noop.jpeg?lk3s=bfd515bb\u0026x-expires=1762578000\u0026x-signature=2a9wlOuANEZ4qFIqxgDwgfCvOAI%3D\u0026from=3218412987","https://p9-sign.douyinpic.com/tos-cn-p-0015/o87ZAyNieC2fkr0LNgCprIVhIA90IwBV1BYAiB~noop.jpeg?lk3s=bfd515bb\u0026x-expires=1762578000\u0026x-signature=21pb73HIX%2FpcbG6oOaizsIw%2BTxM%3D\u0026from=3218412987"]},"word_sub_board":null,"word_type":1},{"article_detail_count":0,"aweme_infos":null,"can_extend_detail":false,"discuss_video_count":1,"display_style":0,"drift_info":null,"event_time":1762524043,"group_id":"7567713329591244041","hot_value":11228146,"hotlist_param":"{\"version\":1}","label":3,"position":3,"related_words":null,"sentence_id":"2298487","sentence_tag":4003,"video_count":1,"view_count":64137949,"word":"峰会之外的乌镇","word_cover":{"uri":"tos-cn-p-0015/oUGBy9SbXX7zID5BLyAgeggG2A6aGCDCcIefvi","url_list":["https://p3-sign.douyinpic.com/tos-cn-p-0015/oUGBy9SbXX7zID5BLyAgeggG2A6aGCDCcIefvi~noop.jpeg?lk3s=bfd515bb\u0026x-expires=1762578000\u0026x-signature=7vysRz3mPygBTLYTvRtwTRaaw3E%3D\u0026from=3218412987","https://p11-sign.douyinpic.com/tos-cn-p-0015/oUGBy9SbXX7zID5BLyAgeggG2A6aGCDCcIefvi~noop.jpeg?lk3s=bfd515bb\u0026x-expires=1762578000\u0026x-signature=L%2BKrD05nBGIM8Jszg1OhLeL6oIg%3D\u0026from=3218412987","https://p26-sign.douyinpic.com/tos-cn-p-0015/oUGBy9SbXX7zID5BLyAgeggG2A6aGCDCcIefvi~noop.jpeg?lk3s=bfd515bb\u0026x-expires=1762578000\u0026x-signature=PzqsVNmVlS9tUcpRh%2Fs9%2B4DbEak%3D\u0026from=3218412987"]},"word_sub_board":null,"word_type":1},{"article_detail_count":1,"aweme_infos":null,"can_extend_detail":false,"discuss_video_count":1,"display_style":0,"drift_info":null,"event_time":1762516818,"group_id":"7048160373825180939","hot_value":11210297,"hotlist_param":"{\"version\":1}","label":3,"position":4,"related_words":null,"sentence_id":"2298352","sentence_tag":3001,"video_count":4,"view_count":57403830,"word":"西安市委书记方红卫被查","word_cover":{"uri":"tos-cn-p-0015/ooeoY8SdMCQkW3DD5bQv3yg7NEMgisCAef25eA","url_list":["https://p3-sign.douyinpic.com/tos-cn-p-0015/ooeoY8SdMCQkW3DD5bQv3yg7NEMgisCAef25eA~noop.jpeg?lk3s=bfd515bb\u0026x-expires=1762578000\u0026x-signature=TqRzHqpyz6n03EFCExidIugmW0I%3D\u0026from=3218412987","https://p11-sign.douyinpic.com/tos-cn-p-0015/ooeoY8SdMCQkW3DD5bQv3yg7NEMgisCAef25eA~noop.jpeg?lk3s=bfd515bb\u0026x-expires=1762578000\u0026x-signature=NysJlwV08L9Hs8fr3CTZaMkn0xM%3D\u0026from=3218412987","https://p26-sign.douyinpic.com/tos-cn-p-0015/ooeoY8SdMCQkW3DD5bQv3yg7NEMgisCAef25eA~noop.jpeg?lk3s=bfd515bb\u0026x-expires=1762578000\u0026x-signature=cqfbIG90Fhn%2FLESFAUo48FeN72I%3D\u0026from=3218412987"]},"word_sub_board":null,"word_type":1},{"article_detail_count":0,"aweme_infos":null,"can_extend_detail":false,"discuss_video_count":1,"display_style":0,"drift_info":null,"event_time":1762495173,"group_id":"7557020934776853810","hot_value":10589142,"hotlist_param":"{\"version\":1}","label":0,"position":5,"related_words":null,"sentence_id":"2297821","sentence_tag":5000,"video_count":3,"view_count":60185221,"word":"泽旺vs努力库瓦提","word_cover":{"uri":"tos-cn-p-0015/ow9WfADGYaABAF7mSqfdfBEBAEBMClMI2lwME8","url_list":["https://p11-sign.douyinpic.com/tos-cn-p-0015/ow9WfADGYaABAF7mSqfdfBEBAEBMClMI2lwME8~noop.jpeg?lk3s=bfd515bb\u0026x-expires=1762578000\u0026x-signature=s3fu9%2BegCFjsPJ1J9KnW8F1xNoc%3D\u0026from=3218412987","https://p3-sign.douyinpic.com/tos-cn-p-0015/ow9WfADGYaABAF7mSqfdfBEBAEBMClMI2lwME8~noop.jpeg?lk3s=bfd515bb\u0026x-expires=1762578000\u0026x-signature=ZhmFulwcReERpxaH8W8%2BwUQ4VTM%3D\u0026from=3218412987","https://p26-sign.douyinpic.com/tos-cn-p-0015/ow9WfADGYaABAF7mSqfdfBEBAEBMClMI2lwME8~noop.jpeg?lk3s=bfd515bb\u0026x-expires=1762578000\u0026x-signature=jzZYDjAZBF3Re7PLnG7U2zzRytc%3D\u0026from=3218412987"]},"word_sub_board":null,"word_type":1},{"article_detail_count":0,"aweme_infos":null,"can_extend_detail":false,"discuss_video_count":1,"display_style":0,"drift_info":null,"event_time":1762519061,"group_id":"7567967705518855467","hot_value":10501374,"hotlist_param":"{\"version\":1}","label":3,"position":6,"related_words":null,"sentence_id":"2298390","sentence_tag":3002,"video_count":1,"view_count":54594765,"word":"美政府最严重“停摆”持续","word_cover":{"uri":"tos-cn-p-0015/oEZIgi8B9epEpA3fNa0Dkd2hulGBABivCJUAR1","url_list":["https://p26-sign.douyinpic.com/tos-cn-p-0015/oEZIgi8B9epEpA3fNa0Dkd2hulGBABivCJUAR1~noop.jpeg?lk3s=bfd515bb\u0026x-expires=1762578000\u0026x-signature=1NJ%2BaJ%2FrLj%2BnucLmjcK7a6MpQRc%3D\u0026from=3218412987","https://p3-sign.douyinpic.com/tos-cn-p-0015/oEZIgi8B9epEpA3fNa0Dkd2hulGBABivCJUAR1~noop.jpeg?lk3s=bfd515bb\u0026x-expires=1762578000\u0026x-signature=P%2FcqYnykCVOGVPPqi16zGkp1Zq0%3D\u0026from=3218412987","https://p9-sign.douyinpic.com/tos-cn-p-0015/oEZIgi8B9epEpA3fNa0Dkd2hulGBABivCJUAR1~noop.jpeg?lk3s=bfd515bb\u0026x-expires=1762578000\u0026x-signature=4KqgTeRVioU6d%2FG%2FytvMvmQn6Pw%3D\u0026from=3218412987"]},"word_sub_board":null,"word_type":1},{"article_detail_count":0,"aweme_infos":null,"can_extend_detail":false,"discuss_video_count":1,"display_style":0,"drift_info":null,"event_time":1762489004,"group_id":"7456054647704048936","hot_value":9329494,"hotlist_param":"{\"version\":1}","label":0,"position":7,"related_words":null,"sentence_id":"2297683","sentence_tag":2002,"video_count":3,"view_count":58583939,"word":"操控游戏好看吗","word_cover":{"uri":"tos-cn-p-0015/ootrIJiDMyNPMvJLAGBAIchzeU0grBcAtdiCfU","url_list":["https://p9-sign.douyinpic.com/tos-cn-p-0015/ootrIJiDMyNPMvJLAGBAIchzeU0grBcAtdiCfU~noop.jpeg?lk3s=bfd515bb\u0026x-expires=1762578000\u0026x-signature=R5yUbPV%2FEw9HQF2yl3N1qqgmUDs%3D\u0026from=3218412987","https://p26-sign.douyinpic.com/tos-cn-p-0015/ootrIJiDMyNPMvJLAGBAIchzeU0grBcAtdiCfU~noop.jpeg?lk3s=bfd515bb\u0026x-expires=1762578000\u0026x-signature=IGkmD5lVypTF457S7Z2R671Khoo%3D\u0026from=3218412987","https://p3-sign.douyinpic.com/tos-cn-p-0015/ootrIJiDMyNPMvJLAGBAIchzeU0grBcAtdiCfU~noop.jpeg?lk3s=bfd515bb\u0026x-expires=1762578000\u0026x-signature=YXIzzjGBYLlFroAE7J8ywsWYkqw%3D\u0026from=3218412987"]},"word_sub_board":null,"word_type":1},{"article_detail_count":0,"aweme_infos":null,"can_extend_detail":false,"discuss_video_count":1,"display_style":0,"drift_info":null,"event_time":1762507496,"group_id":"7569057966679135540","hot_value":9277693,"hotlist_param":"{\"version\":1}","label":0,"position":8,"related_words":null,"sentence_id":"2298180","sentence_tag":20002,"video_count":1,"view_count":56708164,"word":"福建舰喊你穿秋裤","word_cover":{"uri":"tos-cn-p-0015/oEYiwABkIbeC0yr2Gf7sNItZ0XdukBQThDigAA","url_list":["https://p26-sign.douyinpic.com/tos-cn-p-0015/oEYiwABkIbeC0yr2Gf7sNItZ0XdukBQThDigAA~noop.jpeg?lk3s=bfd515bb\u0026x-expires=1762578000\u0026x-signature=BDFopbD6szXiAIwrtGPLUrCk3cU%3D\u0026from=3218412987","https://p3-sign.douyinpic.com/tos-cn-p-0015/oEYiwABkIbeC0yr2Gf7sNItZ0XdukBQThDigAA~noop.jpeg?lk3s=bfd515bb\u0026x-expires=1762578000\u0026x-signature=sSox8sqqIG4vPEvgt%2BhhX7Fz1SQ%3D\u0026from=3218412987","https://p11-sign.douyinpic.com/tos-cn-p-0015/oEYiwABkIbeC0yr2Gf7sNItZ0XdukBQThDigAA~noop.jpeg?lk3s=bfd515bb\u0026x-expires=1762578000\u0026x-signature=xtOJ9IvyXRnCue6BQbBWRq5DTkU%3D\u0026from=3218412987"]},"word_sub_board":null,"word_type":1},{"article_detail_count":0,"aweme_infos":null,"can_extend_detail":false,"discuss_video_count":1,"display_style":0,"drift_info":null,"event_time":1762512750,"group_id":"7569024191501473083","hot_value":9230563,"hotlist_param":"{\"version\":1}","label":5,"position":9,"related_words":null,"sentence_id":"2298318","sentence_tag":2002,"video_count":3,"view_count":50081942,"word":"树影迷宫大结局好现实","word_cover":{"uri":"tos-cn-p-0015/oofrQwN9sAdNC4DvATgF8DaYIfsmp2EB8Ci6ZA","url_list":["https://p26-sign.douyinpic.com/tos-cn-p-0015/oofrQwN9sAdNC4DvATgF8DaYIfsmp2EB8Ci6ZA~noop.jpeg?lk3s=bfd515bb\u0026x-expires=1762578000\u0026x-signature=rMcByPdtxK%2FssdChRXCw1ihYccg%3D\u0026from=3218412987","https://p3-sign.douyinpic.com/tos-cn-p-0015/oofrQwN9sAdNC4DvATgF8DaYIfsmp2EB8Ci6ZA~noop.jpeg?lk3s=bfd515bb\u0026x-expires=1762578000\u0026x-signature=Ewwl4A0P%2Bj4wKh3pekYQTC%2BBVQk%3D\u0026from=3218412987","https://p9-sign.douyinpic.com/tos-cn-p-0015/oofrQwN9sAdNC4DvATgF8DaYIfsmp2EB8Ci6ZA~noop.jpeg?lk3s=bfd515bb\u0026x-expires=1762578000\u0026x-signature=C%2B0jV6U8WgfrD0%2BciggxH9AfbSg%3D\u0026from=3218412987"]},"word_sub_board":null,"word_type":1},{"article_detail_count":0,"aweme_infos":null,"can_extend_detail":false,"discuss_video_count":1,"display_style":0,"drift_info":null,"event_time":1762510512,"group_id":"7567592237665948969","hot_value":9213378,"hotlist_param":"{\"version\":1}","label":0,"position":10,"related_words":null,"sentence_id":"2298264","sentence_tag":20002,"video_count":1,"view_count":49196680,"word":"云南bigbang清唱也好听","word_cover":{"uri":"tos-cn-p-0015/o83VQPia4qqAiNA6PEwBaA1PQkrIIQyBiobi2","url_list":["https://p26-sign.douyinpic.com/tos-cn-p-0015/o83VQPia4qqAiNA6PEwBaA1PQkrIIQyBiobi2~noop.jpeg?lk3s=bfd515bb\u0026x-expires=1762578000\u0026x-signature=ZZgZdVRCY8EoZLFmazOt5LUmdw4%3D\u0026from=3218412987","https://p9-sign.douyinpic.com/tos-cn-p-0015/o83VQPia4qqAiNA6PEwBaA1PQkrIIQyBiobi2~noop.jpeg?lk3s=bfd515bb\u0026x-expires=1762578000\u0026x-signature=3rU3hXt7elf%2Ba86qRHBAfmmmvaw%3D\u0026from=3218412987","https://p3-sign.douyinpic.com/tos-cn-p-0015/o83VQPia4qqAiNA6PEwBaA1PQkrIIQyBiobi2~noop.jpeg?lk3s=bfd515bb\u0026x-expires=1762578000\u0026x-signature=Hp70WE2Yu5CZfsEFMrMxZgPyyBg%3D\u0026from=3218412987"]},"word_sub_board":null,"word_type":1},{"article_detail_count":0,"aweme_infos":null,"can_extend_detail":false,"discuss_video_count":1,"display_style":0,"drift_info":null,"event_time":1762499914,"group_id":"6758975401432716557","hot_value":9126604,"hotlist_param":"{\"version\":1}","label":0,"position":11,"related_words":null,"sentence_id":"2297968","sentence_tag":2005,"video_count":3,"view_count":52846881,"word":"谢霆锋苏州演唱会","word_cover":{"uri":"tos-cn-p-0015c000-ce/oQme3hiUuvvr8NnZA6pwlgwEBfAIiEAbUBq0sI","url_list":["https://p3-sign.douyinpic.com/tos-cn-p-0015c000-ce/oQme3hiUuvvr8NnZA6pwlgwEBfAIiEAbUBq0sI~noop.jpeg?lk3s=bfd515bb\u0026x-expires=1762578000\u0026x-signature=sHe79CEJb4Cg6JrjSHMum8P%2Fy%2BE%3D\u0026from=3218412987","https://p11-sign.douyinpic.com/tos-cn-p-0015c000-ce/oQme3hiUuvvr8NnZA6pwlgwEBfAIiEAbUBq0sI~noop.jpeg?lk3s=bfd515bb\u0026x-expires=1762578000\u0026x-signature=56ZGXKoFsFK%2B8ifKPZdJExODlBs%3D\u0026from=3218412987","https://p26-sign.douyinpic.com/tos-cn-p-0015c000-ce/oQme3hiUuvvr8NnZA6pwlgwEBfAIiEAbUBq0sI~noop.jpeg?lk3s=bfd515bb\u0026x-expires=1762578000\u0026x-signature=VpS%2BQqg4cfn%2FgN0Xu6Kk%2BorSbzY%3D\u0026from=3218412987"]},"word_sub_board":null,"word_type":1},{"article_detail_count":0,"aweme_infos":null,"can_extend_detail":false,"discuss_video_count":1,"display_style":0,"drift_info":null,"event_time":1762434715,"group_id":"7568412629266945321","hot_value":9123340,"hotlist_param":"{\"version\":1}","label":16,"position":12,"related_words":null,"sentence_id":"2297148","sentence_tag":4003,"video_count":6,"view_count":53318515,"word":"成都龙泉山否认举办荒野求生赛","word_cover":{"uri":"tos-cn-p-0015/okeeLI7GS4BaByrYCtLIAFGZBGA7UEXQQcePEP","url_list":["https://p26-sign.douyinpic.com/tos-cn-p-0015/okeeLI7GS4BaByrYCtLIAFGZBGA7UEXQQcePEP~noop.jpeg?lk3s=bfd515bb\u0026x-expires=1762578000\u0026x-signature=cuTcwE9KxfdV8mzVe8duWK8zRbM%3D\u0026from=3218412987","https://p3-sign.douyinpic.com/tos-cn-p-0015/okeeLI7GS4BaByrYCtLIAFGZBGA7UEXQQcePEP~noop.jpeg?lk3s=bfd515bb\u0026x-expires=1762578000\u0026x-signature=RXOGQH%2FdMW2whKWj1WTYjPacjoE%3D\u0026from=3218412987","https://p11-sign.douyinpic.com/tos-cn-p-0015/okeeLI7GS4BaByrYCtLIAFGZBGA7UEXQQcePEP~noop.jpeg?lk3s=bfd515bb\u0026x-expires=1762578000\u0026x-signature=0rZIN1H3i%2Fd2vjJ5y6dYeWbJl%2FI%3D\u0026from=3218412987"]},"word_sub_board":null,"word_type":1},{"article_detail_count":0,"aweme_infos":null,"can_extend_detail":false,"discuss_video_count":1,"display_style":0,"drift_info":null,"event_time":1762525061,"group_id":"6795477634579977484","hot_value":9111521,"hotlist_param":"{\"version\":1}","label":0,"position":13,"related_words":null,"sentence_id":"2298508","sentence_tag":4003,"video_count":1,"view_count":49824310,"word":"日本流感疫情扩散","word_cover":{"uri":"tos-cn-p-0015/o4Le2higggABrNNxAouL9DgIBfAviACFBBH0vI","url_list":["https://p9-sign.douyinpic.com/tos-cn-p-0015/o4Le2higggABrNNxAouL9DgIBfAviACFBBH0vI~noop.jpeg?lk3s=bfd515bb\u0026x-expires=1762578000\u0026x-signature=Wr4EG5O%2F5lhGILhuDBG6y0ZGI1s%3D\u0026from=3218412987","https://p26-sign.douyinpic.com/tos-cn-p-0015/o4Le2higggABrNNxAouL9DgIBfAviACFBBH0vI~noop.jpeg?lk3s=bfd515bb\u0026x-expires=1762578000\u0026x-signature=tIkqoM8JTUfYlVJZaMMm1L%2Bdhyw%3D\u0026from=3218412987","https://p3-sign.douyinpic.com/tos-cn-p-0015/o4Le2higggABrNNxAouL9DgIBfAviACFBBH0vI~noop.jpeg?lk3s=bfd515bb\u0026x-expires=1762578000\u0026x-signature=bVUbulnanlBfG%2BSxu%2BeBSkCK1ck%3D\u0026from=3218412987"]},"word_sub_board":null,"word_type":1},{"article_detail_count":0,"aweme_infos":null,"can_extend_detail":false,"discuss_video_count":1,"display_style":0,"drift_info":null,"event_time":1762507281,"group_id":"6820770067752424711","hot_value":9100137,"hotlist_param":"{\"version\":1}","label":0,"position":14,"related_words":null,"sentence_id":"2298177","sentence_tag":4007,"video_count":9,"view_count":52417909,"word":"沙僧扮演者刘大刚去世","word_cover":{"uri":"tos-cn-p-0015c000-ce/okNjfLC78GSQGLBktgzxAVMfEezPUzJIJTI52A","url_list":["https://p26-sign.douyinpic.com/tos-cn-p-0015c000-ce/okNjfLC78GSQGLBktgzxAVMfEezPUzJIJTI52A~noop.jpeg?lk3s=bfd515bb\u0026x-expires=1762578000\u0026x-signature=xogUWP7yZAFTqHChwwCsEaxhIb8%3D\u0026from=3218412987","https://p3-sign.douyinpic.com/tos-cn-p-0015c000-ce/okNjfLC78GSQGLBktgzxAVMfEezPUzJIJTI52A~noop.jpeg?lk3s=bfd515bb\u0026x-expires=1762578000\u0026x-signature=eckTlsOGlNIbEDPXopggcLDZjU4%3D\u0026from=3218412987","https://p11-sign.douyinpic.com/tos-cn-p-0015c000-ce/okNjfLC78GSQGLBktgzxAVMfEezPUzJIJTI52A~noop.jpeg?lk3s=bfd515bb\u0026x-expires=1762578000\u0026x-signature=q%2FxtmWeLEpxGGcxPb%2FWlpRBeKmU%3D\u0026from=3218412987"]},"word_sub_board":null,"word_type":1},{"article_detail_count":0,"aweme_infos":null,"can_extend_detail":false,"discuss_video_count":1,"display_style":0,"drift_info":null,"event_time":1762491703,"group_id":"7567522994915775807","hot_value":8693971,"hotlist_param":"{\"version\":1}","label":0,"position":15,"related_words":null,"sentence_id":"2297732","sentence_tag":9000,"video_count":3,"view_count":45724578,"word":"糖醋鸡丝饼看着就香","word_cover":{"uri":"tos-cn-i-0813c000-ce/ognt3L7BIIAEgkGfTMe9iAbA7Af1SG8gJAs6EW","url_list":["https://p3-sign.douyinpic.com/tos-cn-i-0813c000-ce/ognt3L7BIIAEgkGfTMe9iAbA7Af1SG8gJAs6EW~noop.jpeg?lk3s=bfd515bb\u0026x-expires=1762578000\u0026x-signature=MJhUflFCUb49JJeNKjdTSDz8oLk%3D\u0026from=3218412987","https://p26-sign.douyinpic.com/tos-cn-i-0813c000-ce/ognt3L7BIIAEgkGfTMe9iAbA7Af1SG8gJAs6EW~noop.jpeg?lk3s=bfd515bb\u0026x-expires=1762578000\u0026x-signature=IS3IHMDH5ovHIeJYpDU2ahXPL2s%3D\u0026from=3218412987","https://p9-sign.douyinpic.com/tos-cn-i-0813c000-ce/ognt3L7BIIAEgkGfTMe9iAbA7Af1SG8gJAs6EW~noop.jpeg?lk3s=bfd515bb\u0026x-expires=1762578000\u0026x-signature=iKekbDMZ7%2FNMGEfYuKKzWwS%2BQiw%3D\u0026from=3218412987"]},"word_sub_board":null,"word_type":1},{"article_detail_count":0,"aweme_infos":null,"can_extend_detail":false,"discuss_video_count":1,"display_style":0,"drift_info":null,"event_time":1762481044,"group_id":"6720130451958142216","hot_value":8008657,"hotlist_param":"{\"version\":1}","label":0,"position":16,"related_words":null,"sentence_id":"2297483","sentence_tag":20002,"video_count":3,"view_count":49098145,"word":"座山雕穿搭","word_cover":{"uri":"tos-cn-p-0015c000-ce/oABmYyQgOlAFuEe5gh7pqEf6xPDAJDeQyDNSmJ","url_list":["https://p26-sign.douyinpic.com/tos-cn-p-0015c000-ce/oABmYyQgOlAFuEe5gh7pqEf6xPDAJDeQyDNSmJ~noop.jpeg?lk3s=bfd515bb\u0026x-expires=1762578000\u0026x-signature=otpvMvtXXL1Zhrolq%2Fpa20yUPnE%3D\u0026from=3218412987","https://p3-sign.douyinpic.com/tos-cn-p-0015c000-ce/oABmYyQgOlAFuEe5gh7pqEf6xPDAJDeQyDNSmJ~noop.jpeg?lk3s=bfd515bb\u0026x-expires=1762578000\u0026x-signature=lczL1qFBlQszMqks5PnjEvKaa7s%3D\u0026from=3218412987","https://p11-sign.douyinpic.com/tos-cn-p-0015c000-ce/oABmYyQgOlAFuEe5gh7pqEf6xPDAJDeQyDNSmJ~noop.jpeg?lk3s=bfd515bb\u0026x-expires=1762578000\u0026x-signature=ooyeeJIz%2FZ5b%2BTYPp5zX1bhTlNU%3D\u0026from=3218412987"]},"word_sub_board":null,"word_type":1},{"article_detail_count":0,"aweme_infos":null,"can_extend_detail":false,"discuss_video_count":1,"display_style":0,"drift_info":null,"event_time":1762509976,"group_id":"7565523992137848114","hot_value":7867877,"hotlist_param":"{\"version\":1}","label":0,"position":17,"related_words":null,"sentence_id":"2298249","sentence_tag":9000,"video_count":3,"view_count":43692478,"word":"固体杨枝甘露冰糖葫芦","word_cover":{"uri":"tos-cn-p-0015/oYIUziBeCB04h9AvmgVdATDCIf7gyPAiqqIZED","url_list":["https://p3-sign.douyinpic.com/tos-cn-p-0015/oYIUziBeCB04h9AvmgVdATDCIf7gyPAiqqIZED~noop.jpeg?lk3s=bfd515bb\u0026x-expires=1762578000\u0026x-signature=volgIIw089FWwXM7682JDvDe4qg%3D\u0026from=3218412987","https://p26-sign.douyinpic.com/tos-cn-p-0015/oYIUziBeCB04h9AvmgVdATDCIf7gyPAiqqIZED~noop.jpeg?lk3s=bfd515bb\u0026x-expires=1762578000\u0026x-signature=DgQKtxMJxxtW11hNkx8obWe7dPs%3D\u0026from=3218412987","https://p11-sign.douyinpic.com/tos-cn-p-0015/oYIUziBeCB04h9AvmgVdATDCIf7gyPAiqqIZED~noop.jpeg?lk3s=bfd515bb\u0026x-expires=1762578000\u0026x-signature=SteddtgpU9%2FvngXOAkFYD7j7%2FVI%3D\u0026from=3218412987"]},"word_sub_board":null,"word_type":1},{"article_detail_count":0,"aweme_infos":null,"can_extend_detail":false,"discuss_video_count":1,"display_style":0,"drift_info":null,"event_time":1762500225,"group_id":"7568942487118288163","hot_value":7844384,"hotlist_param":"{\"version\":1}","label":0,"position":18,"related_words":null,"sentence_id":"2297973","sentence_tag":5000,"video_count":3,"view_count":39279842,"word":"赵鸿刚准备眼睛手术","word_cover":{"uri":"tos-cn-p-0015/o8UAPdpeHi9BE5jAFYA8YIIDNgECDQVBk4fjNr","url_list":["https://p3-sign.douyinpic.com/tos-cn-p-0015/o8UAPdpeHi9BE5jAFYA8YIIDNgECDQVBk4fjNr~noop.jpeg?lk3s=bfd515bb\u0026x-expires=1762578000\u0026x-signature=5XPxnIOpdOIQtS9e4EbF0P58e3I%3D\u0026from=3218412987","https://p26-sign.douyinpic.com/tos-cn-p-0015/o8UAPdpeHi9BE5jAFYA8YIIDNgECDQVBk4fjNr~noop.jpeg?lk3s=bfd515bb\u0026x-expires=1762578000\u0026x-signature=zjiRsbRG8F7C52llnmPCNT8fw9Q%3D\u0026from=3218412987","https://p11-sign.douyinpic.com/tos-cn-p-0015/o8UAPdpeHi9BE5jAFYA8YIIDNgECDQVBk4fjNr~noop.jpeg?lk3s=bfd515bb\u0026x-expires=1762578000\u0026x-signature=3ZfD3%2FgouVPq3i0eB%2BWRqDC2gzo%3D\u0026from=3218412987"]},"word_sub_board":null,"word_type":1},{"article_detail_count":0,"aweme_infos":null,"can_extend_detail":false,"discuss_video_count":1,"display_style":0,"drift_info":null,"event_time":1762510180,"group_id":"7566623122109076799","hot_value":7842196,"hotlist_param":"{\"version\":1}","label":3,"position":19,"related_words":null,"sentence_id":"2298258","sentence_tag":20002,"video_count":3,"view_count":42838529,"word":"跟着董宇辉云逛进博会","word_cover":{"uri":"tos-cn-p-0015/o4fhmjNAKpeMIgEQrQ1FmAJDB2qiDI9Mx3NACA","url_list":["https://p11-sign.douyinpic.com/tos-cn-p-0015/o4fhmjNAKpeMIgEQrQ1FmAJDB2qiDI9Mx3NACA~noop.jpeg?lk3s=bfd515bb\u0026x-expires=1762578000\u0026x-signature=08hPG8otx8vyc5%2B27BS1AwEqotE%3D\u0026from=3218412987","https://p3-sign.douyinpic.com/tos-cn-p-0015/o4fhmjNAKpeMIgEQrQ1FmAJDB2qiDI9Mx3NACA~noop.jpeg?lk3s=bfd515bb\u0026x-expires=1762578000\u0026x-signature=cPJ0tZS3JtVpiZ5xDKnb7soJiC8%3D\u0026from=3218412987","https://p26-sign.douyinpic.com/tos-cn-p-0015/o4fhmjNAKpeMIgEQrQ1FmAJDB2qiDI9Mx3NACA~noop.jpeg?lk3s=bfd515bb\u0026x-expires=1762578000\u0026x-signature=781S7GqibOOyR0V89LHvqewQTOM%3D\u0026from=3218412987"]},"word_sub_board":null,"word_type":1},{"article_detail_count":0,"aweme_infos":null,"can_extend_detail":false,"discuss_video_count":1,"display_style":0,"drift_info":null,"event_time":1762497824,"group_id":"7568540768421385515","hot_value":7832666,"hotlist_param":"{\"version\":1}","label":5,"position":20,"related_words":null,"sentence_id":"2297900","sentence_tag":2002,"video_count":3,"view_count":41247289,"word":"四喜老人坦白弃养外孙女","word_cover":{"uri":"tos-cn-p-0015/o0xJIDDqYBAN5rmx2ni9Ae0CcA4gvBQhIUfsMi","url_list":["https://p3-sign.douyinpic.com/tos-cn-p-0015/o0xJIDDqYBAN5rmx2ni9Ae0CcA4gvBQhIUfsMi~noop.jpeg?lk3s=bfd515bb\u0026x-expires=1762578000\u0026x-signature=QsAwCXyp4uQatBZHYlcNZxc8rzk%3D\u0026from=3218412987","https://p11-sign.douyinpic.com/tos-cn-p-0015/o0xJIDDqYBAN5rmx2ni9Ae0CcA4gvBQhIUfsMi~noop.jpeg?lk3s=bfd515bb\u0026x-expires=1762578000\u0026x-signature=162XnXY24X6t1uo%2Fg0PQlYA130A%3D\u0026from=3218412987","https://p26-sign.douyinpic.com/tos-cn-p-0015/o0xJIDDqYBAN5rmx2ni9Ae0CcA4gvBQhIUfsMi~noop.jpeg?lk3s=bfd515bb\u0026x-expires=1762578000\u0026x-signature=ZcQ2rB58UCA2w3S9GxvSfpk2exI%3D\u0026from=3218412987"]},"word_sub_board":null,"word_type":1},{"article_detail_count":0,"aweme_infos":null,"can_extend_detail":false,"discuss_video_count":1,"display_style":0,"drift_info":null,"event_time":1762494749,"group_id":"7223308031760127292","hot_value":7819149,"hotlist_param":"{\"version\":1}","label":0,"position":21,"related_words":null,"sentence_id":"2297813","sentence_tag":21000,"video_count":9,"view_count":38764970,"word":"中国海军进入“三航母时代”","word_cover":{"uri":"tos-cn-p-0015/o4INNpXAWBYQLg9M5wIAIFEAbhDhzDFBWfeauC","url_list":["https://p26-sign.douyinpic.com/tos-cn-p-0015/o4INNpXAWBYQLg9M5wIAIFEAbhDhzDFBWfeauC~noop.jpeg?lk3s=bfd515bb\u0026x-expires=1762578000\u0026x-signature=LeF%2B7sGBnn6qhmWvc1vqSnbx4nI%3D\u0026from=3218412987","https://p11-sign.douyinpic.com/tos-cn-p-0015/o4INNpXAWBYQLg9M5wIAIFEAbhDhzDFBWfeauC~noop.jpeg?lk3s=bfd515bb\u0026x-expires=1762578000\u0026x-signature=i57hLvAqCm4Bgm7698Hooc66ARY%3D\u0026from=3218412987","https://p3-sign.douyinpic.com/tos-cn-p-0015/o4INNpXAWBYQLg9M5wIAIFEAbhDhzDFBWfeauC~noop.jpeg?lk3s=bfd515bb\u0026x-expires=1762578000\u0026x-signature=PAUtupush64gbcJ5yjqMSb5Fa%2F0%3D\u0026from=3218412987"]},"word_sub_board":null,"word_type":1},{"article_detail_count":0,"aweme_infos":null,"can_extend_detail":false,"discuss_video_count":1,"display_style":0,"drift_info":null,"event_time":1762517988,"group_id":"7567693930079753535","hot_value":7816828,"hotlist_param":"{\"version\":1}","label":3,"position":22,"related_words":null,"sentence_id":"2298371","sentence_tag":2002,"video_count":2,"view_count":35940552,"word":"四喜一部剧凑齐三代熟脸","word_cover":{"uri":"tos-cn-p-0015/owlbMCNBpBt4N4kiiLsLWAIZAA2MfDugp9IwAe","url_list":["https://p3-sign.douyinpic.com/tos-cn-p-0015/owlbMCNBpBt4N4kiiLsLWAIZAA2MfDugp9IwAe~noop.jpeg?lk3s=bfd515bb\u0026x-expires=1762578000\u0026x-signature=HC2weIJMThrVUZQu9GAvXnAcZ8M%3D\u0026from=3218412987","https://p11-sign.douyinpic.com/tos-cn-p-0015/owlbMCNBpBt4N4kiiLsLWAIZAA2MfDugp9IwAe~noop.jpeg?lk3s=bfd515bb\u0026x-expires=1762578000\u0026x-signature=xaGmgs40w%2BWr4DgtxIjhkG1ORuY%3D\u0026from=3218412987","https://p9-sign.douyinpic.com/tos-cn-p-0015/owlbMCNBpBt4N4kiiLsLWAIZAA2MfDugp9IwAe~noop.jpeg?lk3s=bfd515bb\u0026x-expires=1762578000\u0026x-signature=BKJseqbserSHAJVUulfXECR4Tlc%3D\u0026from=3218412987"]},"word_sub_board":null,"word_type":1},{"article_detail_count":0,"aweme_infos":null,"can_extend_detail":false,"discuss_video_count":1,"display_style":0,"drift_info":null,"event_time":1762495504,"group_id":"7569014293204243727","hot_value":7781251,"hotlist_param":"{\"version\":1}","label":3,"position":23,"related_words":null,"sentence_id":"2297831","sentence_tag":2001,"video_count":3,"view_count":37868623,"word":"辛芷蕾回应奖项运作争议","word_cover":{"uri":"tos-cn-p-0015/ogFAlCEkKvDT7zAzB9HGFpLBflGCESIBIfIelR","url_list":["https://p26-sign.douyinpic.com/tos-cn-p-0015/ogFAlCEkKvDT7zAzB9HGFpLBflGCESIBIfIelR~noop.jpeg?lk3s=bfd515bb\u0026x-expires=1762578000\u0026x-signature=sTax%2Bih%2Bzyq8dwAvtqpLFDd29Zw%3D\u0026from=3218412987","https://p11-sign.douyinpic.com/tos-cn-p-0015/ogFAlCEkKvDT7zAzB9HGFpLBflGCESIBIfIelR~noop.jpeg?lk3s=bfd515bb\u0026x-expires=1762578000\u0026x-signature=84kv4EpXte1bQGjpdk6DsIjmGDg%3D\u0026from=3218412987","https://p3-sign.douyinpic.com/tos-cn-p-0015/ogFAlCEkKvDT7zAzB9HGFpLBflGCESIBIfIelR~noop.jpeg?lk3s=bfd515bb\u0026x-expires=1762578000\u0026x-signature=%2BWBk%2F4znywy9bjvHwVWbYT7eKp4%3D\u0026from=3218412987"]},"word_sub_board":null,"word_type":1},{"article_detail_count":0,"aweme_infos":null,"can_extend_detail":false,"discuss_video_count":1,"display_style":0,"drift_info":null,"event_time":1762504374,"group_id":"7568881776723629354","hot_value":7778886,"hotlist_param":"{\"version\":1}","label":3,"position":24,"related_words":null,"sentence_id":"2298107","sentence_tag":2005,"video_count":3,"view_count":32849496,"word":"终于等到茜拉第一条抖音了","word_cover":{"uri":"tos-cn-p-0015c000-ce/oMgMSEEVALJ3BC0BzfpJpf1AQA8AmWUgVg8W7f","url_list":["https://p11-sign.douyinpic.com/tos-cn-p-0015c000-ce/oMgMSEEVALJ3BC0BzfpJpf1AQA8AmWUgVg8W7f~noop.jpeg?lk3s=bfd515bb\u0026x-expires=1762578000\u0026x-signature=pwAtfwjj9uqpCUN6Rh1IhzopzOI%3D\u0026from=3218412987","https://p26-sign.douyinpic.com/tos-cn-p-0015c000-ce/oMgMSEEVALJ3BC0BzfpJpf1AQA8AmWUgVg8W7f~noop.jpeg?lk3s=bfd515bb\u0026x-expires=1762578000\u0026x-signature=2UI8xi35aU9TMt6fY4pwB0q224M%3D\u0026from=3218412987","https://p3-sign.douyinpic.com/tos-cn-p-0015c000-ce/oMgMSEEVALJ3BC0BzfpJpf1AQA8AmWUgVg8W7f~noop.jpeg?lk3s=bfd515bb\u0026x-expires=1762578000\u0026x-signature=HRHrQpcr7YWkZESqL9o9xNSI4wo%3D\u0026from=3218412987"]},"word_sub_board":null,"word_type":1},{"article_detail_count":0,"aweme_infos":null,"can_extend_detail":false,"discuss_video_count":1,"display_style":0,"drift_info":null,"event_time":1762519119,"group_id":"6596114427261490440","hot_value":7773214,"hotlist_param":"{\"version\":1}","label":17,"position":25,"related_words":null,"sentence_id":"2298392","sentence_tag":2012,"video_count":3,"view_count":31843466,"word":"王源生日快乐","word_cover":{"uri":"tos-cn-p-0015c000-ce/oAf3zuHehCEioOcIGIlWx1AL62bwd0iLBAeNiA","url_list":["https://p3-sign.douyinpic.com/tos-cn-p-0015c000-ce/oAf3zuHehCEioOcIGIlWx1AL62bwd0iLBAeNiA~noop.jpeg?lk3s=bfd515bb\u0026x-expires=1762578000\u0026x-signature=noQatVTSIRERk65VYgtPotsUGgk%3D\u0026from=3218412987","https://p26-sign.douyinpic.com/tos-cn-p-0015c000-ce/oAf3zuHehCEioOcIGIlWx1AL62bwd0iLBAeNiA~noop.jpeg?lk3s=bfd515bb\u0026x-expires=1762578000\u0026x-signature=0yapX92y%2Bcbpepi2Hv1%2Fwg7oxnc%3D\u0026from=3218412987","https://p9-sign.douyinpic.com/tos-cn-p-0015c000-ce/oAf3zuHehCEioOcIGIlWx1AL62bwd0iLBAeNiA~noop.jpeg?lk3s=bfd515bb\u0026x-expires=1762578000\u0026x-signature=1A%2BZMrk7mrZT7l3DMg%2FmgY6RPuE%3D\u0026from=3218412987"]},"word_sub_board":null,"word_type":1},{"article_detail_count":0,"aweme_infos":null,"can_extend_detail":false,"discuss_video_count":1,"display_style":0,"drift_info":null,"event_time":1762524809,"group_id":"7569160766763341082","hot_value":7770002,"hotlist_param":"{\"version\":1}","label":8,"position":26,"related_words":null,"sentence_id":"2298505","sentence_tag":2002,"video_count":1,"view_count":31565446,"word":"丁禹兮扮卫韫跳舞太宠我了","word_cover":{"uri":"tos-cn-p-0015/okZIIfUsDAMpFftA3NE9dxQhDBCQKk6giy9hiA","url_list":["https://p26-sign.douyinpic.com/tos-cn-p-0015/okZIIfUsDAMpFftA3NE9dxQhDBCQKk6giy9hiA~noop.jpeg?lk3s=bfd515bb\u0026x-expires=1762578000\u0026x-signature=DazcjK67wElCpG4JHA7QnUIuq8c%3D\u0026from=3218412987","https://p11-sign.douyinpic.com/tos-cn-p-0015/okZIIfUsDAMpFftA3NE9dxQhDBCQKk6giy9hiA~noop.jpeg?lk3s=bfd515bb\u0026x-expires=1762578000\u0026x-signature=Jj8hE1Qq%2FGpYo7mrSh90LKiHXVE%3D\u0026from=3218412987","https://p9-sign.douyinpic.com/tos-cn-p-0015/okZIIfUsDAMpFftA3NE9dxQhDBCQKk6giy9hiA~noop.jpeg?lk3s=bfd515bb\u0026x-expires=1762578000\u0026x-signature=qpXkT2pjxbhV9VSEHTvfSjSvlZc%3D\u0026from=3218412987"]},"word_sub_board":null,"word_type":1},{"article_detail_count":0,"aweme_infos":null,"can_extend_detail":false,"discuss_video_count":1,"display_style":0,"drift_info":null,"event_time":1762500407,"group_id":"6582390978865304846","hot_value":7769743,"hotlist_param":"{\"version\":1}","label":0,"position":27,"related_words":null,"sentence_id":"2297978","sentence_tag":2005,"video_count":3,"view_count":33127229,"word":"张杰贵阳演唱会","word_cover":{"uri":"tos-cn-p-0015c000-ce/oEI70RgYFoZ7tfGICgekL8A8FFQNbf55JJGSkB","url_list":["https://p3-sign.douyinpic.com/tos-cn-p-0015c000-ce/oEI70RgYFoZ7tfGICgekL8A8FFQNbf55JJGSkB~noop.jpeg?lk3s=bfd515bb\u0026x-expires=1762578000\u0026x-signature=Vj2ftQVwD9W5D7s5tpv1ZwWM%2FWc%3D\u0026from=3218412987","https://p26-sign.douyinpic.com/tos-cn-p-0015c000-ce/oEI70RgYFoZ7tfGICgekL8A8FFQNbf55JJGSkB~noop.jpeg?lk3s=bfd515bb\u0026x-expires=1762578000\u0026x-signature=rtJPUX7%2B7n78aIyi3FmdqJZUSqM%3D\u0026from=3218412987","https://p9-sign.douyinpic.com/tos-cn-p-0015c000-ce/oEI70RgYFoZ7tfGICgekL8A8FFQNbf55JJGSkB~noop.jpeg?lk3s=bfd515bb\u0026x-expires=1762578000\u0026x-signature=ELFEt7%2BAgd2P61zZCwqHer7IOZg%3D\u0026from=3218412987"]},"word_sub_board":null,"word_type":1},{"article_detail_count":0,"aweme_infos":null,"can_extend_detail":false,"discuss_video_count":1,"display_style":0,"drift_info":null,"event_time":1762498784,"group_id":"7569209531776767283","hot_value":7762243,"hotlist_param":"{\"version\":1}","label":0,"position":28,"related_words":null,"sentence_id":"2297937","sentence_tag":12000,"video_count":3,"view_count":29398825,"word":"瓦瓦粉丝破四百万","word_cover":{"uri":"tos-cn-p-0015c000-ce/o4NMEMFkDLePi4PMEBDAIhDx9ypwyCIAXMEffD","url_list":["https://p9-sign.douyinpic.com/tos-cn-p-0015c000-ce/o4NMEMFkDLePi4PMEBDAIhDx9ypwyCIAXMEffD~noop.jpeg?lk3s=bfd515bb\u0026x-expires=1762578000\u0026x-signature=URnyURvmxe466BYXfZhltmmN%2B2M%3D\u0026from=3218412987","https://p26-sign.douyinpic.com/tos-cn-p-0015c000-ce/o4NMEMFkDLePi4PMEBDAIhDx9ypwyCIAXMEffD~noop.jpeg?lk3s=bfd515bb\u0026x-expires=1762578000\u0026x-signature=iJ6LJtKFRnpCrdoTO3NqKVT4x58%3D\u0026from=3218412987","https://p3-sign.douyinpic.com/tos-cn-p-0015c000-ce/o4NMEMFkDLePi4PMEBDAIhDx9ypwyCIAXMEffD~noop.jpeg?lk3s=bfd515bb\u0026x-expires=1762578000\u0026x-signature=Lt0eTsSrgqQTDL4Go2myuzU3A2U%3D\u0026from=3218412987"]},"word_sub_board":null,"word_type":1},{"article_detail_count":0,"aweme_infos":null,"can_extend_detail":false,"discuss_video_count":1,"display_style":0,"drift_info":null,"event_time":1762512616,"group_id":"7567738412167140635","hot_value":7760730,"hotlist_param":"{\"version\":1}","label":8,"position":29,"related_words":null,"sentence_id":"2298313","sentence_tag":2002,"video_count":3,"view_count":28598617,"word":"宋茜跳舞纯元回宫","word_cover":{"uri":"tos-cn-p-0015/o4MIgEfC9TdIpAtfNq5DobkWKO3DABFsC49ARl","url_list":["https://p3-sign.douyinpic.com/tos-cn-p-0015/o4MIgEfC9TdIpAtfNq5DobkWKO3DABFsC49ARl~noop.jpeg?lk3s=bfd515bb\u0026x-expires=1762578000\u0026x-signature=sKvozdCJ7IqWyU5D6Co9dw22Hrw%3D\u0026from=3218412987","https://p26-sign.douyinpic.com/tos-cn-p-0015/o4MIgEfC9TdIpAtfNq5DobkWKO3DABFsC49ARl~noop.jpeg?lk3s=bfd515bb\u0026x-expires=1762578000\u0026x-signature=nopH1wziilSh39Q6HukPs1r865s%3D\u0026from=3218412987","https://p9-sign.douyinpic.com/tos-cn-p-0015/o4MIgEfC9TdIpAtfNq5DobkWKO3DABFsC49ARl~noop.jpeg?lk3s=bfd515bb\u0026x-expires=1762578000\u0026x-signature=81FU1TC1RsW079%2B1pMdumzt%2BmUo%3D\u0026from=3218412987"]},"word_sub_board":null,"word_type":1},{"article_detail_count":0,"aweme_infos":null,"can_extend_detail":false,"discuss_video_count":1,"display_style":0,"drift_info":null,"event_time":1762497315,"group_id":"7567708774044554505","hot_value":7756901,"hotlist_param":"{\"version\":1}","label":3,"position":30,"related_words":null,"sentence_id":"2297889","sentence_tag":20002,"video_count":3,"view_count":27294424,"word":"带你发现进博会的爆品好物","word_cover":{"uri":"tos-cn-p-0015/o4IMICBg7b0GAmDS0Fc6fBUvm7eBfE9AEPN4CO","url_list":["https://p9-sign.douyinpic.com/tos-cn-p-0015/o4IMICBg7b0GAmDS0Fc6fBUvm7eBfE9AEPN4CO~noop.jpeg?lk3s=bfd515bb\u0026x-expires=1762578000\u0026x-signature=HHKySrP8em72sAwoRT%2FzO7%2Bfpyw%3D\u0026from=3218412987","https://p26-sign.douyinpic.com/tos-cn-p-0015/o4IMICBg7b0GAmDS0Fc6fBUvm7eBfE9AEPN4CO~noop.jpeg?lk3s=bfd515bb\u0026x-expires=1762578000\u0026x-signature=kf84Zte0hG18Ampq8fXN8RbWZOI%3D\u0026from=3218412987","https://p3-sign.douyinpic.com/tos-cn-p-0015/o4IMICBg7b0GAmDS0Fc6fBUvm7eBfE9AEPN4CO~noop.jpeg?lk3s=bfd515bb\u0026x-expires=1762578000\u0026x-signature=%2BuCqogT7k%2F9E4XlBaNXUfLNvVjo%3D\u0026from=3218412987"]},"word_sub_board":null,"word_type":1},{"article_detail_count":0,"aweme_infos":null,"can_extend_detail":false,"discuss_video_count":1,"display_style":0,"drift_info":null,"event_time":1762484616,"group_id":"6852999997374338311","hot_value":7755181,"hotlist_param":"{\"version\":1}","label":8,"position":31,"related_words":null,"sentence_id":"2297554","sentence_tag":2001,"video_count":3,"view_count":25474755,"word":"电影铁血战士上映","word_cover":{"uri":"tos-cn-p-0015/o0MMBGeGaQVx7eSBHTxWAG3UZCHAfIxxLHvFQA","url_list":["https://p9-sign.douyinpic.com/tos-cn-p-0015/o0MMBGeGaQVx7eSBHTxWAG3UZCHAfIxxLHvFQA~noop.jpeg?lk3s=bfd515bb\u0026x-expires=1762578000\u0026x-signature=RSL2x4x8gRUGrQwFHD%2BIAIZj61c%3D\u0026from=3218412987","https://p26-sign.douyinpic.com/tos-cn-p-0015/o0MMBGeGaQVx7eSBHTxWAG3UZCHAfIxxLHvFQA~noop.jpeg?lk3s=bfd515bb\u0026x-expires=1762578000\u0026x-signature=LTL%2FbOZfGseJymK8Oy46sRfevJQ%3D\u0026from=3218412987","https://p3-sign.douyinpic.com/tos-cn-p-0015/o0MMBGeGaQVx7eSBHTxWAG3UZCHAfIxxLHvFQA~noop.jpeg?lk3s=bfd515bb\u0026x-expires=1762578000\u0026x-signature=%2FrShP7nN5NeS7aGe6b51hXMxeV4%3D\u0026from=3218412987"]},"word_sub_board":null,"word_type":1},{"article_detail_count":0,"aweme_infos":null,"can_extend_detail":false,"discuss_video_count":1,"display_style":0,"drift_info":null,"event_time":1762420426,"group_id":"7567225029248570666","hot_value":7739903,"hotlist_param":"{\"version\":1}","label":0,"position":32,"related_words":null,"sentence_id":"2296887","sentence_tag":20002,"video_count":1,"view_count":24831619,"word":"生活闪亮时：动物先生","word_cover":{"uri":"tos-cn-p-0015/ow0SFFDVQBCEjIvkfBAAQcfFtLKvAO9fH137GY","url_list":["https://p11-sign.douyinpic.com/tos-cn-p-0015/ow0SFFDVQBCEjIvkfBAAQcfFtLKvAO9fH137GY~noop.jpeg?lk3s=bfd515bb\u0026x-expires=1762578000\u0026x-signature=3nX49aLCBnpPTUe84MlkpcMBsWk%3D\u0026from=3218412987","https://p26-sign.douyinpic.com/tos-cn-p-0015/ow0SFFDVQBCEjIvkfBAAQcfFtLKvAO9fH137GY~noop.jpeg?lk3s=bfd515bb\u0026x-expires=1762578000\u0026x-signature=5QxVLahbMSL4uTeJWfwBwP3LkEE%3D\u0026from=3218412987","https://p3-sign.douyinpic.com/tos-cn-p-0015/ow0SFFDVQBCEjIvkfBAAQcfFtLKvAO9fH137GY~noop.jpeg?lk3s=bfd515bb\u0026x-expires=1762578000\u0026x-signature=%2BWvt5VWbpVt6rIocyNYGcKhNESQ%3D\u0026from=3218412987"]},"word_sub_board":null,"word_type":1},{"article_detail_count":0,"aweme_infos":null,"can_extend_detail":false,"discuss_video_count":1,"display_style":0,"drift_info":null,"event_time":1762509547,"group_id":"7568834478983402804","hot_value":7738411,"hotlist_param":"{\"version\":1}","label":3,"position":33,"related_words":null,"sentence_id":"2298227","sentence_tag":6000,"video_count":1,"view_count":20875811,"word":"我把御三家主机合体了","word_cover":{"uri":"tos-cn-p-0015/ogeRLno00SeWIAIPo00LVBuGCHTWGI7NOfEABB","url_list":["https://p3-sign.douyinpic.com/tos-cn-p-0015/ogeRLno00SeWIAIPo00LVBuGCHTWGI7NOfEABB~noop.jpeg?lk3s=bfd515bb\u0026x-expires=1762578000\u0026x-signature=v%2BjtNq0HmLhRYupr7jWXtiy%2FZQw%3D\u0026from=3218412987","https://p11-sign.douyinpic.com/tos-cn-p-0015/ogeRLno00SeWIAIPo00LVBuGCHTWGI7NOfEABB~noop.jpeg?lk3s=bfd515bb\u0026x-expires=1762578000\u0026x-signature=FwMmPhzA9HyjiKFz45uRuVFTTZ4%3D\u0026from=3218412987","https://p26-sign.douyinpic.com/tos-cn-p-0015/ogeRLno00SeWIAIPo00LVBuGCHTWGI7NOfEABB~noop.jpeg?lk3s=bfd515bb\u0026x-expires=1762578000\u0026x-signature=futn8X1rXFMU8DVIFiNMTDERBCQ%3D\u0026from=3218412987"]},"word_sub_board":null,"word_type":1},{"article_detail_count":0,"aweme_infos":null,"can_extend_detail":false,"discuss_video_count":1,"display_style":0,"drift_info":null,"event_time":1762396398,"group_id":"7196688725354239267","hot_value":7722503,"hotlist_param":"{\"version\":1}","label":9,"position":34,"related_words":null,"sentence_id":"2296321","sentence_tag":1001,"video_count":3,"view_count":22272718,"word":"对方拒绝了你的道德绑架","word_cover":{"uri":"tos-cn-p-0015c000-ce/oAG7ExgCwUv9AIIWpvQY4UF2AdEIeOf5CcCaDe","url_list":["https://p26-sign.douyinpic.com/tos-cn-p-0015c000-ce/oAG7ExgCwUv9AIIWpvQY4UF2AdEIeOf5CcCaDe~noop.jpeg?lk3s=bfd515bb\u0026x-expires=1762578000\u0026x-signature=VKBb5XF%2BC7FFCxdCawtJhXG%2BwuM%3D\u0026from=3218412987","https://p3-sign.douyinpic.com/tos-cn-p-0015c000-ce/oAG7ExgCwUv9AIIWpvQY4UF2AdEIeOf5CcCaDe~noop.jpeg?lk3s=bfd515bb\u0026x-expires=1762578000\u0026x-signature=IyS3GsrSTAp6su08iJ8ugBTPn2Y%3D\u0026from=3218412987","https://p11-sign.douyinpic.com/tos-cn-p-0015c000-ce/oAG7ExgCwUv9AIIWpvQY4UF2AdEIeOf5CcCaDe~noop.jpeg?lk3s=bfd515bb\u0026x-expires=1762578000\u0026x-signature=9SWb3g2IhBZv7nS9G%2BBbZkqrmvw%3D\u0026from=3218412987"]},"word_sub_board":[3],"word_type":1},{"article_detail_count":0,"aweme_infos":null,"can_extend_detail":false,"discuss_video_count":1,"display_style":0,"drift_info":null,"event_time":1762485580,"group_id":"7312018542739559690","hot_value":7721730,"hotlist_param":"{\"version\":1}","label":0,"position":35,"related_words":null,"sentence_id":"2297589","sentence_tag":20002,"video_count":3,"view_count":20497533,"word":"这个冬天不能没有毛茸茸","word_cover":{"uri":"tos-cn-p-0015/o8P8TDNDpBLkBZfFEB2C2AEuAAaMfD1g79I7ck","url_list":["https://p3-sign.douyinpic.com/tos-cn-p-0015/o8P8TDNDpBLkBZfFEB2C2AEuAAaMfD1g79I7ck~noop.jpeg?lk3s=bfd515bb\u0026x-expires=1762578000\u0026x-signature=ynYy0XLfeAMkoV%2BPfIXpu0EbzLY%3D\u0026from=3218412987","https://p26-sign.douyinpic.com/tos-cn-p-0015/o8P8TDNDpBLkBZfFEB2C2AEuAAaMfD1g79I7ck~noop.jpeg?lk3s=bfd515bb\u0026x-expires=1762578000\u0026x-signature=99Fwfzag2Wz%2B5On9Wadrarfw2WI%3D\u0026from=3218412987","https://p11-sign.douyinpic.com/tos-cn-p-0015/o8P8TDNDpBLkBZfFEB2C2AEuAAaMfD1g79I7ck~noop.jpeg?lk3s=bfd515bb\u0026x-expires=1762578000\u0026x-signature=qo2CIsGNJqGnHRJagNO1sOK7rEc%3D\u0026from=3218412987"]},"word_sub_board":null,"word_type":1},{"article_detail_count":0,"aweme_infos":null,"can_extend_detail":false,"discuss_video_count":1,"display_style":0,"drift_info":null,"event_time":1762485119,"group_id":"7564423234981795118","hot_value":7717112,"hotlist_param":"{\"version\":1}","label":5,"position":36,"related_words":null,"sentence_id":"2297572","sentence_tag":9000,"video_count":3,"view_count":17350908,"word":"约顿火锅是我的立冬宣言","word_cover":{"uri":"tos-cn-p-0015/ogtDA8frNAa2MfQgIesQABEMeCKWgPBQkYnEUA","url_list":["https://p3-sign.douyinpic.com/tos-cn-p-0015/ogtDA8frNAa2MfQgIesQABEMeCKWgPBQkYnEUA~noop.jpeg?lk3s=bfd515bb\u0026x-expires=1762578000\u0026x-signature=lIb%2B6SstRedaqaaOQ0rrgr2dddc%3D\u0026from=3218412987","https://p26-sign.douyinpic.com/tos-cn-p-0015/ogtDA8frNAa2MfQgIesQABEMeCKWgPBQkYnEUA~noop.jpeg?lk3s=bfd515bb\u0026x-expires=1762578000\u0026x-signature=fxIT%2Bcl57pCu2z4ScazEwJYdhDk%3D\u0026from=3218412987","https://p11-sign.douyinpic.com/tos-cn-p-0015/ogtDA8frNAa2MfQgIesQABEMeCKWgPBQkYnEUA~noop.jpeg?lk3s=bfd515bb\u0026x-expires=1762578000\u0026x-signature=DU0pUys%2FJ0an%2FLIV6N3V2gJ41NU%3D\u0026from=3218412987"]},"word_sub_board":null,"word_type":1},{"article_detail_count":0,"aweme_infos":null,"can_extend_detail":false,"discuss_video_count":1,"display_style":0,"drift_info":null,"event_time":1762521433,"group_id":"7568989223450219776","hot_value":7714039,"hotlist_param":"{\"version\":1}","label":3,"position":37,"related_words":null,"sentence_id":"2298434","sentence_tag":2003,"video_count":1,"view_count":17682688,"word":"薛之谦 中国唱将师资团里的魔丸","word_cover":{"uri":"tos-cn-p-0015c000-ce/oMSk8CNi6C3IeAF7eJkIrXBA7GBSgxfAQy7DEo","url_list":["https://p3-sign.douyinpic.com/tos-cn-p-0015c000-ce/oMSk8CNi6C3IeAF7eJkIrXBA7GBSgxfAQy7DEo~noop.jpeg?lk3s=bfd515bb\u0026x-expires=1762578000\u0026x-signature=wAMmGnnWIbLnayEX1I7GEggD00o%3D\u0026from=3218412987","https://p26-sign.douyinpic.com/tos-cn-p-0015c000-ce/oMSk8CNi6C3IeAF7eJkIrXBA7GBSgxfAQy7DEo~noop.jpeg?lk3s=bfd515bb\u0026x-expires=1762578000\u0026x-signature=Arh3lrm3Sa%2FEjZeDdBSOG4YWvbs%3D\u0026from=3218412987","https://p11-sign.douyinpic.com/tos-cn-p-0015c000-ce/oMSk8CNi6C3IeAF7eJkIrXBA7GBSgxfAQy7DEo~noop.jpeg?lk3s=bfd515bb\u0026x-expires=1762578000\u0026x-signature=MdZ2DG2oscoQaSo1827pOKPDbPM%3D\u0026from=3218412987"]},"word_sub_board":null,"word_type":1},{"article_detail_count":0,"aweme_infos":null,"can_extend_detail":false,"discuss_video_count":1,"display_style":0,"drift_info":null,"event_time":1762411608,"group_id":"7566619789851596073","hot_value":7706221,"hotlist_param":"{\"version\":1}","label":0,"position":38,"related_words":null,"sentence_id":"2296685","sentence_tag":9000,"video_count":3,"view_count":15596463,"word":"热乎乎的美食打卡地图","word_cover":{"uri":"tos-cn-p-0015/oAJCDffhAEEDIroPGJpgFBVLIt96ApTWYAs0Bm","url_list":["https://p26-sign.douyinpic.com/tos-cn-p-0015/oAJCDffhAEEDIroPGJpgFBVLIt96ApTWYAs0Bm~noop.jpeg?lk3s=bfd515bb\u0026x-expires=1762578000\u0026x-signature=ixNsvHjc2UOSrs%2FVY6J0CF6agvs%3D\u0026from=3218412987","https://p11-sign.douyinpic.com/tos-cn-p-0015/oAJCDffhAEEDIroPGJpgFBVLIt96ApTWYAs0Bm~noop.jpeg?lk3s=bfd515bb\u0026x-expires=1762578000\u0026x-signature=qYIDFNf9KCxgLnvT48Wlaogl0gM%3D\u0026from=3218412987","https://p3-sign.douyinpic.com/tos-cn-p-0015/oAJCDffhAEEDIroPGJpgFBVLIt96ApTWYAs0Bm~noop.jpeg?lk3s=bfd515bb\u0026x-expires=1762578000\u0026x-signature=xS8M3jA8M4KxdaVNDPWwzeqUiDg%3D\u0026from=3218412987"]},"word_sub_board":null,"word_type":1},{"article_detail_count":0,"aweme_infos":null,"can_extend_detail":false,"discuss_video_count":1,"display_style":0,"drift_info":null,"event_time":1762502669,"group_id":"7567617032101270793","hot_value":7705063,"hotlist_param":"{\"version\":1}","label":3,"position":39,"related_words":null,"sentence_id":"2298059","sentence_tag":12000,"video_count":3,"view_count":13404359,"word":"白泽赏金赛bbFps15杀清图","word_cover":{"uri":"tos-cn-p-0015c000-ce/osRM9fwIEaDADo5FMMBYIpz36UjE9AB3EJlJfT","url_list":["https://p3-sign.douyinpic.com/tos-cn-p-0015c000-ce/osRM9fwIEaDADo5FMMBYIpz36UjE9AB3EJlJfT~noop.jpeg?lk3s=bfd515bb\u0026x-expires=1762578000\u0026x-signature=HkG%2FoTvPgU9BSu7btSlz9quMprs%3D\u0026from=3218412987","https://p11-sign.douyinpic.com/tos-cn-p-0015c000-ce/osRM9fwIEaDADo5FMMBYIpz36UjE9AB3EJlJfT~noop.jpeg?lk3s=bfd515bb\u0026x-expires=1762578000\u0026x-signature=%2FPuasCoCOTUbRnolfUj0UxonkD4%3D\u0026from=3218412987","https://p26-sign.douyinpic.com/tos-cn-p-0015c000-ce/osRM9fwIEaDADo5FMMBYIpz36UjE9AB3EJlJfT~noop.jpeg?lk3s=bfd515bb\u0026x-expires=1762578000\u0026x-signature=v0dM5ALKriMSjoE4itim4YzVkVU%3D\u0026from=3218412987"]},"word_sub_board":null,"word_type":1},{"article_detail_count":0,"aweme_infos":null,"can_extend_detail":false,"discuss_video_count":1,"display_style":0,"drift_info":null,"event_time":1762493794,"group_id":"7567549131423487295","hot_value":7702306,"hotlist_param":"{\"version\":1}","label":3,"position":40,"related_words":null,"sentence_id":"2297785","sentence_tag":2012,"video_count":1,"view_count":13559461,"word":"等到了蓝盈莹相见时难别亦难转场","word_cover":{"uri":"tos-cn-p-0015c000-ce/oMB2IOjFx0MovYIxwA8Zs0AZiTaPwJMYkiQIP","url_list":["https://p11-sign.douyinpic.com/tos-cn-p-0015c000-ce/oMB2IOjFx0MovYIxwA8Zs0AZiTaPwJMYkiQIP~noop.jpeg?lk3s=bfd515bb\u0026x-expires=1762578000\u0026x-signature=GSOIQJFKDdj9AyYl0cpmDPUFl88%3D\u0026from=3218412987","https://p26-sign.douyinpic.com/tos-cn-p-0015c000-ce/oMB2IOjFx0MovYIxwA8Zs0AZiTaPwJMYkiQIP~noop.jpeg?lk3s=bfd515bb\u0026x-expires=1762578000\u0026x-signature=l%2FdcI986EmyNffCQY0X1cJo7nt4%3D\u0026from=3218412987","https://p3-sign.douyinpic.com/tos-cn-p-0015c000-ce/oMB2IOjFx0MovYIxwA8Zs0AZiTaPwJMYkiQIP~noop.jpeg?lk3s=bfd515bb\u0026x-expires=1762578000\u0026x-signature=tRAF1eqp%2FI9v140XiX0bF3T9LUI%3D\u0026from=3218412987"]},"word_sub_board":null,"word_type":1},{"article_detail_count":0,"aweme_infos":null,"can_extend_detail":false,"discuss_video_count":1,"display_style":0,"drift_info":null,"event_time":1762500322,"group_id":"7510290997106169138","hot_value":7688878,"hotlist_param":"{\"version\":1}","label":0,"position":41,"related_words":null,"sentence_id":"2297974","sentence_tag":3002,"video_count":2,"view_count":11426159,"word":"中方回应日本水产品输华","word_cover":{"uri":"tos-cn-p-0015/o8qyot4WBIwDON1AAXiBCzebBBfy0zAIingwAh","url_list":["https://p3-sign.douyinpic.com/tos-cn-p-0015/o8qyot4WBIwDON1AAXiBCzebBBfy0zAIingwAh~noop.jpeg?lk3s=bfd515bb\u0026x-expires=1762578000\u0026x-signature=esPEJtRfzzZnJxy1XpHCq%2BQLKBs%3D\u0026from=3218412987","https://p9-sign.douyinpic.com/tos-cn-p-0015/o8qyot4WBIwDON1AAXiBCzebBBfy0zAIingwAh~noop.jpeg?lk3s=bfd515bb\u0026x-expires=1762578000\u0026x-signature=kwrLUvLIfHpsh5IN2Gj39HvhBTw%3D\u0026from=3218412987","https://p11-sign.douyinpic.com/tos-cn-p-0015/o8qyot4WBIwDON1AAXiBCzebBBfy0zAIingwAh~noop.jpeg?lk3s=bfd515bb\u0026x-expires=1762578000\u0026x-signature=bRdWDKB9iHE3eZ6bzP4UL2w1isE%3D\u0026from=3218412987"]},"word_sub_board":null,"word_type":1},{"article_detail_count":0,"aweme_infos":null,"can_extend_detail":false,"discuss_video_count":1,"display_style":0,"drift_info":null,"event_time":1762482366,"group_id":"7567262783952672050","hot_value":7685049,"hotlist_param":"{\"version\":1}","label":0,"position":42,"related_words":null,"sentence_id":"2297500","sentence_tag":3001,"video_count":2,"view_count":10103583,"word":"苏州副市长唐晓东被查","word_cover":{"uri":"tos-cn-p-0015/o8bSGCifwABfH7PFAIL3GVEGdeqo3FqIBBCwNI","url_list":["https://p3-sign.douyinpic.com/tos-cn-p-0015/o8bSGCifwABfH7PFAIL3GVEGdeqo3FqIBBCwNI~noop.jpeg?lk3s=bfd515bb\u0026x-expires=1762578000\u0026x-signature=J%2BQBrD4YQ9HHgxumNmboFHSB0yY%3D\u0026from=3218412987","https://p11-sign.douyinpic.com/tos-cn-p-0015/o8bSGCifwABfH7PFAIL3GVEGdeqo3FqIBBCwNI~noop.jpeg?lk3s=bfd515bb\u0026x-expires=1762578000\u0026x-signature=6ozAQhuWrSjkUkxqU1ltEktA0JE%3D\u0026from=3218412987","https://p26-sign.douyinpic.com/tos-cn-p-0015/o8bSGCifwABfH7PFAIL3GVEGdeqo3FqIBBCwNI~noop.jpeg?lk3s=bfd515bb\u0026x-expires=1762578000\u0026x-signature=o42zElW4zij882Om1sbUeDymTvw%3D\u0026from=3218412987"]},"word_sub_board":null,"word_type":1},{"article_detail_count":0,"aweme_infos":null,"can_extend_detail":false,"discuss_video_count":1,"display_style":0,"drift_info":null,"event_time":1762496784,"group_id":"7569014180054390068","hot_value":7675556,"hotlist_param":"{\"version\":1}","label":3,"position":43,"related_words":null,"sentence_id":"2297871","sentence_tag":2003,"video_count":3,"view_count":9237663,"word":"张柏芝因病中断一路繁花2录制","word_cover":{"uri":"tos-cn-p-0015/oopSQOteFAmwC7wQAELwGhGGVe1ofbwIBBCsNI","url_list":["https://p3-sign.douyinpic.com/tos-cn-p-0015/oopSQOteFAmwC7wQAELwGhGGVe1ofbwIBBCsNI~noop.jpeg?lk3s=bfd515bb\u0026x-expires=1762578000\u0026x-signature=upLhbY%2FoxSfBVG14omoIAoAlc8o%3D\u0026from=3218412987","https://p26-sign.douyinpic.com/tos-cn-p-0015/oopSQOteFAmwC7wQAELwGhGGVe1ofbwIBBCsNI~noop.jpeg?lk3s=bfd515bb\u0026x-expires=1762578000\u0026x-signature=RLXTpm3%2F1T3ByfYT4pf2R2s7siE%3D\u0026from=3218412987","https://p9-sign.douyinpic.com/tos-cn-p-0015/oopSQOteFAmwC7wQAELwGhGGVe1ofbwIBBCsNI~noop.jpeg?lk3s=bfd515bb\u0026x-expires=1762578000\u0026x-signature=1JjkidUuLaEzmNhZEOfepa%2Bmh%2Bw%3D\u0026from=3218412987"]},"word_sub_board":null,"word_type":1},{"article_detail_count":0,"aweme_infos":null,"can_extend_detail":false,"discuss_video_count":1,"display_style":0,"drift_info":null,"event_time":1762473577,"group_id":"7568868750260671744","hot_value":7673416,"hotlist_param":"{\"version\":1}","label":0,"position":44,"related_words":null,"sentence_id":"2297379","sentence_tag":20002,"video_count":2,"view_count":6823767,"word":"麦小登拆房了","word_cover":{"uri":"tos-cn-p-0015/oceBOiAFEixf0yhMC0Z9AlNMZjIAIiwtBjamig","url_list":["https://p3-sign.douyinpic.com/tos-cn-p-0015/oceBOiAFEixf0yhMC0Z9AlNMZjIAIiwtBjamig~noop.jpeg?lk3s=bfd515bb\u0026x-expires=1762578000\u0026x-signature=vqFqgBR9bmNO1QqGwPjKqKE6V98%3D\u0026from=3218412987","https://p11-sign.douyinpic.com/tos-cn-p-0015/oceBOiAFEixf0yhMC0Z9AlNMZjIAIiwtBjamig~noop.jpeg?lk3s=bfd515bb\u0026x-expires=1762578000\u0026x-signature=0Z%2B4ufosmzAud0ePGGhE30zBvKU%3D\u0026from=3218412987","https://p26-sign.douyinpic.com/tos-cn-p-0015/oceBOiAFEixf0yhMC0Z9AlNMZjIAIiwtBjamig~noop.jpeg?lk3s=bfd515bb\u0026x-expires=1762578000\u0026x-signature=DD8tO2Q9OO3CBgTWGjfzLpS5xfY%3D\u0026from=3218412987"]},"word_sub_board":null,"word_type":1},{"article_detail_count":0,"aweme_infos":null,"can_extend_detail":false,"discuss_video_count":1,"display_style":0,"drift_info":null,"event_time":1762526343,"group_id":"7568238437255697727","hot_value":7672649,"hotlist_param":"{\"version\":1}","label":17,"position":45,"related_words":null,"sentence_id":"2298530","sentence_tag":2012,"video_count":1,"view_count":6358375,"word":"TF四代嗯嗯嗯撒娇舞","word_cover":{"uri":"tos-cn-p-0015c000-ce/oQEvM4XiaPrP2BJGkxoSRAInN1QIIh3RA6iQZ","url_list":["https://p3-sign.douyinpic.com/tos-cn-p-0015c000-ce/oQEvM4XiaPrP2BJGkxoSRAInN1QIIh3RA6iQZ~noop.jpeg?lk3s=bfd515bb\u0026x-expires=1762578000\u0026x-signature=3%2FZkNwXnUeTBZ%2FBgLMPtX1KscXk%3D\u0026from=3218412987","https://p11-sign.douyinpic.com/tos-cn-p-0015c000-ce/oQEvM4XiaPrP2BJGkxoSRAInN1QIIh3RA6iQZ~noop.jpeg?lk3s=bfd515bb\u0026x-expires=1762578000\u0026x-signature=HMxM7smVn2qG1FW%2FixN4GsblaEg%3D\u0026from=3218412987","https://p26-sign.douyinpic.com/tos-cn-p-0015c000-ce/oQEvM4XiaPrP2BJGkxoSRAInN1QIIh3RA6iQZ~noop.jpeg?lk3s=bfd515bb\u0026x-expires=1762578000\u0026x-signature=716SKZmVFoJgdJhwcx94LCWed88%3D\u0026from=3218412987"]},"word_sub_board":null,"word_type":1},{"article_detail_count":0,"aweme_infos":null,"can_extend_detail":false,"discuss_video_count":1,"display_style":0,"drift_info":null,"event_time":1762508461,"group_id":"7523133993068483880","hot_value":7669848,"hotlist_param":"{\"version\":1}","label":3,"position":46,"related_words":null,"sentence_id":"2298206","sentence_tag":2002,"video_count":3,"view_count":5530635,"word":"魔幻手机之猪哥外传","word_cover":{"uri":"tos-cn-p-0015c000-ce/owAMElR05tQ7ZEiuAkIPaMiBBxcHXdxZiHvx2","url_list":["https://p3-sign.douyinpic.com/tos-cn-p-0015c000-ce/owAMElR05tQ7ZEiuAkIPaMiBBxcHXdxZiHvx2~noop.jpeg?lk3s=bfd515bb\u0026x-expires=1762578000\u0026x-signature=PKRULSN6u%2Ff1PQ6HRm64Sag4AgY%3D\u0026from=3218412987","https://p9-sign.douyinpic.com/tos-cn-p-0015c000-ce/owAMElR05tQ7ZEiuAkIPaMiBBxcHXdxZiHvx2~noop.jpeg?lk3s=bfd515bb\u0026x-expires=1762578000\u0026x-signature=0qgkimNysjNN2WOW9M9rfB9vDt4%3D\u0026from=3218412987","https://p26-sign.douyinpic.com/tos-cn-p-0015c000-ce/owAMElR05tQ7ZEiuAkIPaMiBBxcHXdxZiHvx2~noop.jpeg?lk3s=bfd515bb\u0026x-expires=1762578000\u0026x-signature=UtLavw6OreD5cCU8GcjVpDGqLYQ%3D\u0026from=3218412987"]},"word_sub_board":null,"word_type":1},{"article_detail_count":0,"aweme_infos":null,"can_extend_detail":false,"discuss_video_count":1,"display_style":0,"drift_info":null,"event_time":1762503669,"group_id":"7569033591155791119","hot_value":7667964,"hotlist_param":"{\"version\":1}","label":3,"position":47,"related_words":null,"sentence_id":"2298094","sentence_tag":5000,"video_count":1,"view_count":3856973,"word":"樊振东和林诗栋同台对练","word_cover":{"uri":"tos-cn-p-0015/oQPAwII9jtBl2X4QwHCKAIaopvNpPgIiZ9iQv","url_list":["https://p3-sign.douyinpic.com/tos-cn-p-0015/oQPAwII9jtBl2X4QwHCKAIaopvNpPgIiZ9iQv~noop.jpeg?lk3s=bfd515bb\u0026x-expires=1762578000\u0026x-signature=PlT9HHbcGEMETkqQuHHKBzAznUk%3D\u0026from=3218412987","https://p26-sign.douyinpic.com/tos-cn-p-0015/oQPAwII9jtBl2X4QwHCKAIaopvNpPgIiZ9iQv~noop.jpeg?lk3s=bfd515bb\u0026x-expires=1762578000\u0026x-signature=HkzVdkDXnzcaEvN40HQiZspA7r0%3D\u0026from=3218412987","https://p11-sign.douyinpic.com/tos-cn-p-0015/oQPAwII9jtBl2X4QwHCKAIaopvNpPgIiZ9iQv~noop.jpeg?lk3s=bfd515bb\u0026x-expires=1762578000\u0026x-signature=sprncBCM1mQVgn8spNns6nlZYUg%3D\u0026from=3218412987"]},"word_sub_board":null,"word_type":1},{"article_detail_count":0,"aweme_infos":null,"can_extend_detail":false,"discuss_video_count":1,"display_style":0,"drift_info":null,"event_time":1762518704,"group_id":"7569863841921750281","hot_value":7664506,"hotlist_param":"{\"version\":1}","label":0,"position":48,"related_words":null,"sentence_id":"2298386","sentence_tag":5000,"video_count":3,"view_count":2811011,"word":"C罗说贝克汉姆“除了脸都一般”","word_cover":{"uri":"tos-cn-p-0015/oYIrN05AZBrjGgeJwiIA0iiAQaB7HhDpMfpgED","url_list":["https://p11-sign.douyinpic.com/tos-cn-p-0015/oYIrN05AZBrjGgeJwiIA0iiAQaB7HhDpMfpgED~noop.jpeg?lk3s=bfd515bb\u0026x-expires=1762578000\u0026x-signature=bvKTYasi4rj%2FPV1U055efSaaBoQ%3D\u0026from=3218412987","https://p26-sign.douyinpic.com/tos-cn-p-0015/oYIrN05AZBrjGgeJwiIA0iiAQaB7HhDpMfpgED~noop.jpeg?lk3s=bfd515bb\u0026x-expires=1762578000\u0026x-signature=HuuepBepR3PZgSQV2fA4ekDQz04%3D\u0026from=3218412987","https://p3-sign.douyinpic.com/tos-cn-p-0015/oYIrN05AZBrjGgeJwiIA0iiAQaB7HhDpMfpgED~noop.jpeg?lk3s=bfd515bb\u0026x-expires=1762578000\u0026x-signature=atkP6gN0lLUM%2FVLlAoS92gUucbE%3D\u0026from=3218412987"]},"word_sub_board":null,"word_type":1},{"article_detail_count":0,"aweme_infos":null,"can_extend_detail":false,"discuss_video_count":1,"display_style":0,"drift_info":null,"event_time":1762472811,"group_id":"7558345354186462506","hot_value":7663080,"hotlist_param":"{\"version\":1}","label":3,"position":49,"related_words":null,"sentence_id":"2297364","sentence_tag":19000,"video_count":2,"view_count":888263,"word":"爸爸答应一万遍不如妈妈答应一遍","word_cover":{"uri":"tos-cn-p-0015/ooIJua8itTeMBIvEuBi0A3EBgrCmiAjofOhApw","url_list":["https://p3-sign.douyinpic.com/tos-cn-p-0015/ooIJua8itTeMBIvEuBi0A3EBgrCmiAjofOhApw~noop.jpeg?lk3s=bfd515bb\u0026x-expires=1762578000\u0026x-signature=8AdP9AV2PWi5rdSmydLcIeGPkFc%3D\u0026from=3218412987","https://p11-sign.douyinpic.com/tos-cn-p-0015/ooIJua8itTeMBIvEuBi0A3EBgrCmiAjofOhApw~noop.jpeg?lk3s=bfd515bb\u0026x-expires=1762578000\u0026x-signature=OaSXnZqo4y3Nk5cqQ1ESgLPqldA%3D\u0026from=3218412987","https://p26-sign.douyinpic.com/tos-cn-p-0015/ooIJua8itTeMBIvEuBi0A3EBgrCmiAjofOhApw~noop.jpeg?lk3s=bfd515bb\u0026x-expires=1762578000\u0026x-signature=A31g%2BJto0xnmrF0hpEzhd0zyU9g%3D\u0026from=3218412987"]},"word_sub_board":null,"word_type":1},{"article_detail_count":0,"aweme_infos":null,"can_extend_detail":false,"discuss_video_count":1,"display_style":0,"drift_info":null,"event_time":1762490533,"group_id":"7568794972897514787","hot_value":7662699,"hotlist_param":"{\"version\":1}","label":3,"position":50,"related_words":null,"sentence_id":"2297711","sentence_tag":21000,"video_count":1,"view_count":592670,"word":"杭州湾将实弹发射训练禁止驶入","word_cover":{"uri":"tos-cn-p-0015/o0haIGXGbGA1aj5BntLfB7SBsB3AuCAGIeezNI","url_list":["https://p26-sign.douyinpic.com/tos-cn-p-0015/o0haIGXGbGA1aj5BntLfB7SBsB3AuCAGIeezNI~noop.jpeg?lk3s=bfd515bb\u0026x-expires=1762578000\u0026x-signature=v7R4g3yVGh7hxWByppj1OMrk1p8%3D\u0026from=3218412987","https://p3-sign.douyinpic.com/tos-cn-p-0015/o0haIGXGbGA1aj5BntLfB7SBsB3AuCAGIeezNI~noop.jpeg?lk3s=bfd515bb\u0026x-expires=1762578000\u0026x-signature=s2%2B4bxBSHZ7hn7w6NV8H3BYmC6w%3D\u0026from=3218412987","https://p11-sign.douyinpic.com/tos-cn-p-0015/o0haIGXGbGA1aj5BntLfB7SBsB3AuCAGIeezNI~noop.jpeg?lk3s=bfd515bb\u0026x-expires=1762578000\u0026x-signature=40ePgOg3YBwa8QQdVfvDt%2FX0JUU%3D\u0026from=3218412987"]},"word_sub_board":null,"word_type":1}]},"extra":{"fatal_item_ids":[],"logid":"202511080719257041795CA6285E5A8A25","now":1762557565000},"log_pb":{"impr_id":"202511080719257041795CA6285E5A8A25"},"status_code":0}